infsumpy/__init__.py
infsumpy/infsum.py
infsumpy/utils.py
infsumpy/methods/__init__.py
infsumpy/methods/fixed_method.py
infsumpy/methods/integral_test_method.py
infsumpy/methods/ratio_test_method.py
infsumpy/methods/threshold_method.py
infsumpy-1.0.5.dist-info/licenses/LICENSE
infsumpy-1.0.5.dist-info/METADATA
infsumpy-1.0.5.dist-info/WHEEL
infsumpy-1.0.5.dist-info/top_level.txt
infsumpy-1.0.5.dist-info/RECORD
