Metadata-Version: 2.4
Name: InfSumPy
Version: 1.0.5
Summary: Approximate infinite sums with guaranteed error.
Home-page: https://github.com/wellington36/InfSumPy
Author: Wellington Silva
Author-email: <wellington.71319@gmail.com>
License: GPL-3.0
Keywords: python,sum,series,infinite-series,approximation,guaranted-sum
License-File: LICENSE
Requires-Dist: mpmath
Dynamic: author
Dynamic: author-email
Dynamic: description
Dynamic: description-content-type
Dynamic: home-page
Dynamic: keywords
Dynamic: license
Dynamic: license-file
Dynamic: requires-dist
Dynamic: summary
